zsx_Phylogenetic_Tree.py
zsx_Phylogenetic_Tree-2.1.0.dist-info/METADATA
zsx_Phylogenetic_Tree-2.1.0.dist-info/WHEEL
zsx_Phylogenetic_Tree-2.1.0.dist-info/top_level.txt
zsx_Phylogenetic_Tree-2.1.0.dist-info/RECORD
